{
    "abuseipdb": "token_here",
    "alienvault": "token_here",
    "criminalip_api_key": "token_here",
    "crowdstrike_client_id": "client_id_here",
    "crowdstrike_client_secret": "client_secret_here",
    "firehol_url": "https://iplists.firehol.org/files/firehol_level3.netset",
    "firehol_cache_timeout": 600,
    "google_safe_browsing": "token_here",
    "ipinfo": "token_here",
    "mde_client_id": "client_id_here",
    "mde_client_secret": "client_secret_here",
    "mde_tenant_id": "tenant_here",
    "misp_api_key": "token_here",
    "misp_url": "https://misp.local",
    "opencti_api_key": "token_here",
    "opencti_url": "https://demo.opencti.io",
    "proxy_url": "",
    "shodan": "token_here",
    "virustotal": "token_here",
    "webscout": "token_here"
}
